spotipyss/__init__.py
spotipyss-0.1.1.dist-info/LICENSE
spotipyss-0.1.1.dist-info/METADATA
spotipyss-0.1.1.dist-info/WHEEL
spotipyss-0.1.1.dist-info/RECORD
